{
  "id_str": "922310545713266688",
  "source": "<a href=\"http://twitter.com/download/iphone\" rel=\"nofollow\">Twitter for iPhone</a>",
  "in_reply_to_status_id": null,
  "created_at": "Mon Oct 23 03:55:44 +0000 2017",
  "retweet_count": 0,
  "truncated": false,
  "place": {
    "id": "0b79f7e718cb54b9",
    "country_code": "AR",
    "name": "C\u00f3rdoba",
    "bounding_box": {
      "coordinates": [
        [
          [
            -65.778264,
            -34.998735
          ],
          [
            -65.778264,
            -29.503325
          ],
          [
            -61.777678,
            -29.503325
          ],
          [
            -61.777678,
            -34.998735
          ]
        ]
      ],
      "type": "Polygon"
    },
    "place_type": "admin",
    "country": "Argentina",
    "full_name": "C\u00f3rdoba, Argentina",
    "url": "https://api.twitter.com/1.1/geo/id/0b79f7e718cb54b9.json",
    "attributes": {}
  },
  "possibly_sensitive": false,
  "text": "si hablaste conmigo y nunca te aburriste porque no s\u00e9 sacar temas realmente hablaste conmigo? https://t.co/wjILZFBx3v",
  "id": 922310545713266688,
  "in_reply_to_screen_name": null,
  "entities": {
    "hashtags": [],
    "urls": [
      {
        "indices": [
          94,
          117
        ],
        "expanded_url": "https://twitter.com/maifroglia1/status/921785588629549056",
        "display_url": "twitter.com/maifroglia1/st\u2026",
        "url": "https://t.co/wjILZFBx3v"
      }
    ],
    "symbols": [],
    "user_mentions": []
  },
  "display_text_range": [
    0,
    93
  ],
  "quoted_status": {
    "quoted_status_id_str": "921130453108711430",
    "geo": null,
    "user": {
      "id_str": "983644057",
      "favourites_count": 10575,
      "contributors_enabled": false,
      "name": "Maia",
      "profile_sidebar_fill_color": "E6F6F9",
      "profile_background_tile": true,
      "profile_background_color": "DBE9ED",
      "created_at": "Sun Dec 02 01:03:56 +0000 2012",
      "profile_banner_url": "https://pbs.twimg.com/profile_banners/983644057/1504149912",
      "location": null,
      "description": null,
      "listed_count": 0,
      "follow_request_sent": null,
      "default_profile_image": false,
      "lang": "es",
      "statuses_count": 5061,
      "url": null,
      "notifications": null,
      "id": 983644057,
      "profile_background_image_url": "http://pbs.twimg.com/profile_background_images/378800000179240792/wH6SwxV9.jpeg",
      "translator_type": "none",
      "screen_name": "MaiFroglia1",
      "protected": false,
      "profile_link_color": "555599",
      "friends_count": 250,
      "time_zone": "Hawaii",
      "profile_background_image_url_https": "https://pbs.twimg.com/profile_background_images/378800000179240792/wH6SwxV9.jpeg",
      "profile_text_color": "333333",
      "is_translator": false,
      "followers_count": 418,
      "default_profile": false,
      "utc_offset": -36000,
      "verified": false,
      "following": null,
      "profile_image_url": "http://pbs.twimg.com/profile_images/903096299515469825/bG_F7CNh_normal.jpg",
      "profile_use_background_image": true,
      "profile_sidebar_border_color": "FFFFFF",
      "geo_enabled": true,
      "profile_image_url_https": "https://pbs.twimg.com/profile_images/903096299515469825/bG_F7CNh_normal.jpg"
    },
    "source": "<a href=\"http://twitter.com/download/iphone\" rel=\"nofollow\">Twitter for iPhone</a>",
    "lang": "es",
    "favorited": false,
    "in_reply_to_status_id": null,
    "created_at": "Sat Oct 21 17:09:44 +0000 2017",
    "coordinates": null,
    "quote_count": 331,
    "truncated": false,
    "place": null,
    "retweet_count": 5764,
    "reply_count": 17,
    "possibly_sensitive": false,
    "text": "Si hablaste conmigo y nunca te mande un \u201cno entend\u00ed\u201d, realmente hablaste conmigo? https://t.co/6LwdG2ivSl",
    "in_reply_to_user_id": null,
    "id": 921785588629549056,
    "favorite_count": 3728,
    "in_reply_to_status_id_str": null,
    "in_reply_to_screen_name": null,
    "entities": {
      "hashtags": [],
      "urls": [
        {
          "indices": [
            82,
            105
          ],
          "expanded_url": "https://twitter.com/valenflecchia/status/921130453108711430",
          "display_url": "twitter.com/valenflecchia/\u2026",
          "url": "https://t.co/6LwdG2ivSl"
        }
      ],
      "symbols": [],
      "user_mentions": []
    },
    "id_str": "921785588629549056",
    "quoted_status_id": 921130453108711430,
    "display_text_range": [
      0,
      81
    ],
    "filter_level": "low",
    "retweeted": false,
    "contributors": null,
    "in_reply_to_user_id_str": null,
    "is_quote_status": true
  },
  "retweeted": false,
  "timestamp_ms": "1508730944456",
  "contributors": null,
  "is_quote_status": true,
  "quoted_status_id_str": "921785588629549056",
  "user": {
    "id_str": "864564966",
    "favourites_count": 11860,
    "contributors_enabled": false,
    "name": "barbi \u2728",
    "profile_sidebar_fill_color": "E5507E",
    "profile_background_tile": true,
    "profile_background_color": "FA743E",
    "created_at": "Sat Oct 06 11:54:48 +0000 2012",
    "profile_banner_url": "https://pbs.twimg.com/profile_banners/864564966/1492206511",
    "location": "Vicu\u00f1a Mackenna,Cba, Argentina",
    "description": "Cerati infinito. Patricio rey.",
    "listed_count": 0,
    "follow_request_sent": null,
    "default_profile_image": false,
    "lang": "es",
    "statuses_count": 28660,
    "url": null,
    "notifications": null,
    "id": 864564966,
    "profile_background_image_url": "http://pbs.twimg.com/profile_background_images/587434751234965506/8xDOagAF.jpg",
    "translator_type": "none",
    "screen_name": "Baarbipr",
    "protected": false,
    "profile_link_color": "94D487",
    "friends_count": 706,
    "time_zone": "Brasilia",
    "profile_background_image_url_https": "https://pbs.twimg.com/profile_background_images/587434751234965506/8xDOagAF.jpg",
    "profile_text_color": "362720",
    "is_translator": false,
    "followers_count": 968,
    "default_profile": false,
    "utc_offset": -7200,
    "verified": false,
    "following": null,
    "profile_image_url": "http://pbs.twimg.com/profile_images/917033559470329856/qZriDSio_normal.jpg",
    "profile_use_background_image": true,
    "profile_sidebar_border_color": "FFFFFF",
    "geo_enabled": true,
    "profile_image_url_https": "https://pbs.twimg.com/profile_images/917033559470329856/qZriDSio_normal.jpg"
  },
  "favorited": false,
  "coordinates": null,
  "quote_count": 0,
  "lang": "es",
  "reply_count": 0,
  "in_reply_to_user_id": null,
  "favorite_count": 0,
  "in_reply_to_status_id_str": null,
  "geo": null,
  "quoted_status_id": 921785588629549056,
  "filter_level": "low",
  "in_reply_to_user_id_str": null
}