{
  "created_at": "Fri May 29 06:28:14 +0000 2009",
  "is_quote_status": false,
  "in_reply_to_user_id": null,
  "in_reply_to_status_id_str": null,
  "in_reply_to_user_id_str": null,
  "id": 1957083056,
  "contributors": null,
  "source": "<a href=\"http://twitter.com\" rel=\"nofollow\">Twitter Web Client</a>",
  "entities": {
    "urls": [],
    "symbols": [],
    "user_mentions": [],
    "hashtags": []
  },
  "user": {
    "created_at": "Tue May 26 23:55:29 +0000 2009",
    "profile_sidebar_fill_color": "F6F6F6",
    "follow_request_sent": false,
    "profile_image_url_https": "https://pbs.twimg.com/profile_images/756996254157053952/tj8qkoyo_normal.jpg",
    "utc_offset": -21600,
    "time_zone": "Mountain Time (US & Canada)",
    "is_translator": false,
    "name": "Rachel",
    "is_translation_enabled": false,
    "default_profile_image": false,
    "has_extended_profile": true,
    "notifications": false,
    "following": false,
    "description": "Life is like a camera. Just focus on what's important, capture the good times, develop from the negatives and if things don't turn out- take another shot.",
    "screen_name": "Rachel_Megan",
    "contributors_enabled": false,
    "protected": false,
    "entities": {
      "description": {
        "urls": []
      }
    },
    "default_profile": false,
    "profile_background_color": "ACDED6",
    "profile_background_image_url_https": "https://abs.twimg.com/images/themes/theme18/bg.gif",
    "profile_link_color": "038543",
    "url": null,
    "favourites_count": 83,
    "profile_banner_url": "https://pbs.twimg.com/profile_banners/42760658/1469393248",
    "translator_type": "none",
    "profile_use_background_image": true,
    "profile_background_tile": false,
    "verified": false,
    "id": 42760658,
    "profile_sidebar_border_color": "EEEEEE",
    "profile_background_image_url": "http://abs.twimg.com/images/themes/theme18/bg.gif",
    "statuses_count": 3382,
    "profile_image_url": "http://pbs.twimg.com/profile_images/756996254157053952/tj8qkoyo_normal.jpg",
    "listed_count": 1,
    "followers_count": 52,
    "friends_count": 106,
    "location": "Texas, USA",
    "geo_enabled": false,
    "lang": "en",
    "profile_text_color": "333333",
    "id_str": "42760658"
  },
  "coordinates": null,
  "retweeted": false,
  "truncated": false,
  "favorited": false,
  "in_reply_to_status_id": null,
  "geo": null,
  "retweet_count": 0,
  "favorite_count": 0,
  "in_reply_to_screen_name": null,
  "id_str": "1957083056",
  "place": null,
  "lang": "en",
  "text": "Can't sleep and nothings on tv!! :-("
}