{
  "created_at": "Tue May 20 16:55:06 +0000 2014",
  "id": 468797072695910400,
  "id_str": "468797072695910400",
  "text": "Para ser Feliz en la vida, Solamente tienes que estar feliz contigo misma....!\ud83d\ude4c\u270c #Feliz #Bendecida\u2764 http://t.co/Tf3Nl3vYWk",
  "truncated": false,
  "entities": {
    "hashtags": [
      {
        "text": "Feliz",
        "indices": [81, 87]
      }, {
        "text": "Bendecida",
        "indices": [88, 98]
      }
    ],
    "symbols": [],
    "user_mentions": [],
    "urls": [],
    "media": [
      {
        "id": 468797069092593664,
        "id_str": "468797069092593664",
        "indices": [100, 122],
        "media_url": "http://pbs.twimg.com/media/BoGAc1cCIAAJpvB.jpg",
        "media_url_https": "https://pbs.twimg.com/media/BoGAc1cCIAAJpvB.jpg",
        "url": "http://t.co/Tf3Nl3vYWk",
        "display_url": "pic.twitter.com/Tf3Nl3vYWk",
        "expanded_url": "https://twitter.com/Perla_Estevez/status/468797072695910400/photo/1",
        "type": "photo",
        "sizes": {
          "thumb": {
            "w": 150,
            "h": 150,
            "resize": "crop"
          },
          "medium": {
            "w": 1200,
            "h": 605,
            "resize": "fit"
          },
          "small": {
            "w": 680,
            "h": 343,
            "resize": "fit"
          },
          "large": {
            "w": 2048,
            "h": 1032,
            "resize": "fit"
          }
        }
      }
    ]
  },
  "extended_entities": {
    "media": [
      {
        "id": 468797069092593664,
        "id_str": "468797069092593664",
        "indices": [100, 122],
        "media_url": "http://pbs.twimg.com/media/BoGAc1cCIAAJpvB.jpg",
        "media_url_https": "https://pbs.twimg.com/media/BoGAc1cCIAAJpvB.jpg",
        "url": "http://t.co/Tf3Nl3vYWk",
        "display_url": "pic.twitter.com/Tf3Nl3vYWk",
        "expanded_url": "https://twitter.com/Perla_Estevez/status/468797072695910400/photo/1",
        "type": "photo",
        "sizes": {
          "thumb": {
            "w": 150,
            "h": 150,
            "resize": "crop"
          },
          "medium": {
            "w": 1200,
            "h": 605,
            "resize": "fit"
          },
          "small": {
            "w": 680,
            "h": 343,
            "resize": "fit"
          },
          "large": {
            "w": 2048,
            "h": 1032,
            "resize": "fit"
          }
        }
      }
    ]
  },
  "source": "<a href=\"http://twitter.com\" rel=\"nofollow\">Twitter Web Client</a>",
  "in_reply_to_status_id": null,
  "in_reply_to_status_id_str": null,
  "in_reply_to_user_id": null,
  "in_reply_to_user_id_str": null,
  "in_reply_to_screen_name": null,
  "user": {
    "id": 409560451,
    "id_str": "409560451",
    "name": "P\u0454\u044f\u2113\u03b1 \u2740",
    "screen_name": "Perla_Estevez",
    "location": "",
    "description": "20/11/12\u2661! Dancer of Belly Dancer!!. Electronic music lover\u267b\u270c | ~Always #TeamTyga\u270c @Tyga Followed me on January 30th 2014 /O/",
    "url": "http://t.co/noOGWWgQCq",
    "entities": {
      "url": {
        "urls": [
          {
            "url": "http://t.co/noOGWWgQCq",
            "expanded_url": "http://instagram.com/perlaestevez",
            "display_url": "instagram.com/perlaestevez",
            "indices": [0, 22]
          }
        ]
      },
      "description": {
        "urls": []
      }
    },
    "protected": false,
    "followers_count": 1218,
    "friends_count": 681,
    "listed_count": 2,
    "created_at": "Thu Nov 10 22:37:55 +0000 2011",
    "favourites_count": 565,
    "utc_offset": -10800,
    "time_zone": "Santiago",
    "geo_enabled": true,
    "verified": false,
    "statuses_count": 22374,
    "lang": "es",
    "contributors_enabled": false,
    "is_translator": false,
    "is_translation_enabled": false,
    "profile_background_color": "4EE807",
    "profile_background_image_url": "http://pbs.twimg.com/profile_background_images/468446019600924672/bPlLpdC8.jpeg",
    "profile_background_image_url_https": "https://pbs.twimg.com/profile_background_images/468446019600924672/bPlLpdC8.jpeg",
    "profile_background_tile": true,
    "profile_image_url": "http://pbs.twimg.com/profile_images/624689568768331776/9goADHiq_normal.jpg",
    "profile_image_url_https": "https://pbs.twimg.com/profile_images/624689568768331776/9goADHiq_normal.jpg",
    "profile_banner_url": "https://pbs.twimg.com/profile_banners/409560451/1437772572",
    "profile_link_color": "3AEB0E",
    "profile_sidebar_border_color": "000000",
    "profile_sidebar_fill_color": "E6F6F9",
    "profile_text_color": "333333",
    "profile_use_background_image": true,
    "has_extended_profile": false,
    "default_profile": false,
    "default_profile_image": false,
    "following": false,
    "follow_request_sent": false,
    "notifications": false,
    "translator_type": "regular"
  },
  "geo": null,
  "coordinates": null,
  "place": null,
  "contributors": null,
  "is_quote_status": false,
  "retweet_count": 1,
  "favorite_count": 2,
  "favorited": false,
  "retweeted": false,
  "possibly_sensitive": false,
  "possibly_sensitive_appealable": false,
  "lang": "es"
}