{
  "created_at": "Wed May 21 03:15:34 +0000 2014",
  "id": 468953217846747138,
  "id_str": "468953217846747138",
  "text": "\"#OLALLA\" the movie , sin poder etiquetar con poca se\u00f1al pero #feliz cumpliendo mis metas http://t.co/FNw1fEgSuK",
  "truncated": false,
  "entities": {
    "hashtags": [
      {
        "text": "OLALLA",
        "indices": [1, 8]
      }, {
        "text": "feliz",
        "indices": [62, 68]
      }
    ],
    "symbols": [],
    "user_mentions": [],
    "urls": [
      {
        "url": "http://t.co/FNw1fEgSuK",
        "expanded_url": "http://fb.me/6PPTPqnre",
        "display_url": "fb.me/6PPTPqnre",
        "indices": [90, 112]
      }
    ]
  },
  "source": "<a href=\"http://www.facebook.com/twitter\" rel=\"nofollow\">Facebook</a>",
  "in_reply_to_status_id": null,
  "in_reply_to_status_id_str": null,
  "in_reply_to_user_id": null,
  "in_reply_to_user_id_str": null,
  "in_reply_to_screen_name": null,
  "user": {
    "id": 1244708898,
    "id_str": "1244708898",
    "name": "Alejandro Loayza",
    "screen_name": "ANTARES__FILMS",
    "location": "",
    "description": "ACTOR - DIRECTOR - PRODUCER CINE movies : Our brand is Crisis, BOQUERON, Norte estrecho",
    "url": null,
    "entities": {
      "description": {
        "urls": []
      }
    },
    "protected": false,
    "followers_count": 185,
    "friends_count": 596,
    "listed_count": 3,
    "created_at": "Tue Mar 05 22:15:23 +0000 2013",
    "favourites_count": 4,
    "utc_offset": null,
    "time_zone": null,
    "geo_enabled": true,
    "verified": false,
    "statuses_count": 4404,
    "lang": "es",
    "contributors_enabled": false,
    "is_translator": false,
    "is_translation_enabled": false,
    "profile_background_color": "000000",
    "profile_background_image_url": "http://abs.twimg.com/images/themes/theme1/bg.png",
    "profile_background_image_url_https": "https://abs.twimg.com/images/themes/theme1/bg.png",
    "profile_background_tile": false,
    "profile_image_url": "http://pbs.twimg.com/profile_images/631789252716679168/oBi_mCHb_normal.jpg",
    "profile_image_url_https": "https://pbs.twimg.com/profile_images/631789252716679168/oBi_mCHb_normal.jpg",
    "profile_banner_url": "https://pbs.twimg.com/profile_banners/1244708898/1442321684",
    "profile_link_color": "3B94D9",
    "profile_sidebar_border_color": "000000",
    "profile_sidebar_fill_color": "000000",
    "profile_text_color": "000000",
    "profile_use_background_image": false,
    "has_extended_profile": false,
    "default_profile": false,
    "default_profile_image": false,
    "following": false,
    "follow_request_sent": false,
    "notifications": false,
    "translator_type": "none"
  },
  "geo": null,
  "coordinates": null,
  "place": null,
  "contributors": null,
  "is_quote_status": false,
  "retweet_count": 0,
  "favorite_count": 0,
  "favorited": false,
  "retweeted": false,
  "possibly_sensitive": false,
  "possibly_sensitive_appealable": false,
  "lang": "es"
}