{
  "source": "<a href=\"http://twitter.com\" rel=\"nofollow\">Twitter Web Client</a>",
  "in_reply_to_status_id_str": null,
  "favorited": false,
  "in_reply_to_user_id": null,
  "geo": null,
  "in_reply_to_screen_name": null,
  "text": "wow the weather is amazing today! :)",
  "in_reply_to_status_id": null,
  "contributors": null,
  "place": null,
  "truncated": false,
  "retweeted": false,
  "entities": {
    "urls": [],
    "symbols": [],
    "user_mentions": [],
    "hashtags": []
  },
  "lang": "en",
  "retweet_count": 0,
  "coordinates": null,
  "id_str": "1753728858",
  "in_reply_to_user_id_str": null,
  "favorite_count": 0,
  "id": 1753728858,
  "user": {
    "profile_background_image_url": "http://abs.twimg.com/images/themes/theme1/bg.png",
    "utc_offset": 3600,
    "default_profile": true,
    "profile_background_image_url_https": "https://abs.twimg.com/images/themes/theme1/bg.png",
    "url": "http://t.co/8qqSm5Y10Z",
    "favourites_count": 122,
    "protected": false,
    "default_profile_image": false,
    "lang": "en",
    "profile_text_color": "333333",
    "profile_sidebar_fill_color": "DDEEF6",
    "profile_use_background_image": true,
    "followers_count": 309,
    "verified": false,
    "location": "KL, Malaysia",
    "listed_count": 21,
    "screen_name": "Stefanvds",
    "name": "Stefanvds",
    "profile_sidebar_border_color": "C0DEED",
    "statuses_count": 24021,
    "entities": {
      "url": {
        "urls": [
          {
            "expanded_url": "http://www.stefanvds.com",
            "display_url": "stefanvds.com",
            "url": "http://t.co/8qqSm5Y10Z",
            "indices": [
              0,
              22
            ]
          }
        ]
      },
      "description": {
        "urls": [
          {
            "expanded_url": "http://stefanvds.com",
            "display_url": "stefanvds.com",
            "url": "http://t.co/SM2TFfISn4",
            "indices": [
              31,
              53
            ]
          }
        ]
      }
    },
    "friends_count": 434,
    "has_extended_profile": false,
    "is_translator": false,
    "is_translation_enabled": false,
    "contributors_enabled": false,
    "profile_background_tile": false,
    "geo_enabled": true,
    "id_str": "17437970",
    "profile_link_color": "1DA1F2",
    "follow_request_sent": false,
    "profile_image_url": "http://pbs.twimg.com/profile_images/494009848757882882/DexMHStf_normal.jpeg",
    "profile_image_url_https": "https://pbs.twimg.com/profile_images/494009848757882882/DexMHStf_normal.jpeg",
    "created_at": "Mon Nov 17 09:11:40 +0000 2008",
    "id": 17437970,
    "description": "ICT, Petrolhead, Photographer, http://t.co/SM2TFfISn4",
    "time_zone": "Brussels",
    "profile_background_color": "C0DEED",
    "translator_type": "none",
    "following": false,
    "notifications": false
  },
  "is_quote_status": false,
  "created_at": "Sun May 10 10:07:46 +0000 2009"
}