{
  "created_at": "Wed Sep 20 17:21:38 +0000 2017",
  "id": 910554556290957317,
  "id_str": "910554556290957317",
  "text": "RT @DroidBorger: BEST NEW POKEMON IN UR LIFE",
  "source": "<a href=\"http://twitter.com/download/android\" rel=\"nofollow\">Twitter for Android</a>",
  "truncated": false,
  "in_reply_to_status_id": null,
  "in_reply_to_status_id_str": null,
  "in_reply_to_user_id": null,
  "in_reply_to_user_id_str": null,
  "in_reply_to_screen_name": null,
  "user": {
    "id": 904706041258151936,
    "id_str": "904706041258151936",
    "name": "\ud83c\udf83Frankie",
    "screen_name": "nightjarred",
    "location": "Athens, GA",
    "url": null,
    "description": "26. Queer biologist. Nerdy. Rural. Coffee flavored. He/him. Kissing @bogpunk a lot right now \u2615",
    "translator_type": "none",
    "protected": false,
    "verified": false,
    "followers_count": 15,
    "friends_count": 75,
    "listed_count": 0,
    "favourites_count": 876,
    "statuses_count": 742,
    "created_at": "Mon Sep 04 14:01:43 +0000 2017",
    "utc_offset": -25200,
    "time_zone": "Pacific Time (US & Canada)",
    "geo_enabled": false,
    "lang": "en",
    "contributors_enabled": false,
    "is_translator": false,
    "profile_background_color": "000000",
    "profile_background_image_url": "http://abs.twimg.com/images/themes/theme1/bg.png",
    "profile_background_image_url_https": "https://abs.twimg.com/images/themes/theme1/bg.png",
    "profile_background_tile": false,
    "profile_link_color": "FF691F",
    "profile_sidebar_border_color": "000000",
    "profile_sidebar_fill_color": "000000",
    "profile_text_color": "000000",
    "profile_use_background_image": false,
    "profile_image_url": "http://pbs.twimg.com/profile_images/909583777596416000/1btOFcNX_normal.jpg",
    "profile_image_url_https": "https://pbs.twimg.com/profile_images/909583777596416000/1btOFcNX_normal.jpg",
    "profile_banner_url": "https://pbs.twimg.com/profile_banners/904706041258151936/1505158143",
    "default_profile": false,
    "default_profile_image": false,
    "following": null,
    "follow_request_sent": null,
    "notifications": null
  },
  "geo": null,
  "coordinates": null,
  "place": null,
  "contributors": null,
  "retweeted_status": {
    "created_at": "Wed Sep 20 16:14:01 +0000 2017",
    "id": 910537541576564736,
    "id_str": "910537541576564736",
    "text": "BEST NEW POKEMON IN UR LIFE",
    "source": "<a href=\"http://www.twitter.com/voidbotger\" rel=\"nofollow\">VoidBot app</a>",
    "truncated": false,
    "in_reply_to_status_id": null,
    "in_reply_to_status_id_str": null,
    "in_reply_to_user_id": null,
    "in_reply_to_user_id_str": null,
    "in_reply_to_screen_name": null,
    "user": {
      "id": 731634208943132672,
      "id_str": "731634208943132672",
      "name": "DroidBorger",
      "screen_name": "DroidBorger",
      "location": null,
      "url": null,
      "description": "VoidBurger_ebooks",
      "translator_type": "none",
      "protected": false,
      "verified": false,
      "followers_count": 153,
      "friends_count": 0,
      "listed_count": 4,
      "favourites_count": 0,
      "statuses_count": 22889,
      "created_at": "Sat May 14 23:56:03 +0000 2016",
      "utc_offset": -25200,
      "time_zone": "Pacific Time (US & Canada)",
      "geo_enabled": false,
      "lang": "en",
      "contributors_enabled": false,
      "is_translator": false,
      "profile_background_color": "000000",
      "profile_background_image_url": "http://abs.twimg.com/images/themes/theme1/bg.png",
      "profile_background_image_url_https": "https://abs.twimg.com/images/themes/theme1/bg.png",
      "profile_background_tile": false,
      "profile_link_color": "FF691F",
      "profile_sidebar_border_color": "000000",
      "profile_sidebar_fill_color": "000000",
      "profile_text_color": "000000",
      "profile_use_background_image": false,
      "profile_image_url": "http://pbs.twimg.com/profile_images/731656328066805761/jPNr0V88_normal.jpg",
      "profile_image_url_https": "https://pbs.twimg.com/profile_images/731656328066805761/jPNr0V88_normal.jpg",
      "default_profile": false,
      "default_profile_image": false,
      "following": null,
      "follow_request_sent": null,
      "notifications": null
    },
    "geo": null,
    "coordinates": null,
    "place": null,
    "contributors": null,
    "is_quote_status": false,
    "quote_count": 0,
    "reply_count": 0,
    "retweet_count": 1,
    "favorite_count": 1,
    "entities": {
      "hashtags": [],
      "urls": [],
      "user_mentions": [],
      "symbols": []
    },
    "favorited": false,
    "retweeted": false,
    "filter_level": "low",
    "lang": "en"
  },
  "is_quote_status": false,
  "quote_count": 0,
  "reply_count": 0,
  "retweet_count": 0,
  "favorite_count": 0,
  "entities": {
    "hashtags": [],
    "urls": [],
    "user_mentions": [
      {
        "screen_name": "DroidBorger",
        "name": "DroidBorger",
        "id": 731634208943132672,
        "id_str": "731634208943132672",
        "indices": [
          3,
          15
        ]
      }
    ],
    "symbols": []
  },
  "favorited": false,
  "retweeted": false,
  "filter_level": "low",
  "lang": "en",
  "timestamp_ms": "1505928098162"
}