{"created_at": "Sat Sep 23 23:19:09 +0000 2017", "id": 911731693815439360, "id_str": "911731693815439360", "text": "\u671d\u304b\u3089\u6687\u3059\u304e\u3044\u3044\u306d\u3057\u305f\u3089\u3044\u304f\u3088", "source": "<a href=\"http://twitter.com/download/android\" rel=\"nofollow\">Twitter for Android</a>", "truncated": false, "in_reply_to_status_id": null, "in_reply_to_status_id_str": null, "in_reply_to_user_id": null, "in_reply_to_user_id_str": null, "in_reply_to_screen_name": null, "user": {"id": 786174948284862464, "id_str": "786174948284862464", "name": "\u308a\u30fc\u304f", "screen_name": "16111611aa", "location": "\u65e5\u672c \u795e\u5948", "url": null, "description": "\u4e2d\u4e8c\uff01\u263a\ud83d\ude03\u307f\u3093\u306a\u660e\u65e5\u3092\u5927\u5207\u306b\u306d\u3002\n\u30d5\u30a9\u30ed\u30d0\u73871000\u307f\u3093\u306a\u30d5\u30a9\u30ed\u30fcRT\u3088\u308d\u3057\u304f\ud83d\ude4f\ud83d\ude1d\ud83d\udc95\u2934\u2934\ud83d\udc99\ud83d\udc97\ud83d\udc8b\ud83d\udc9c\ud83d\udc9a\ud83d\udc96\ud83d\ude1e\ud83d\ude0e\ud83d\udc95\u263a\ud83d\ude09\ud83d\ude0a\ud83d\ude0f\ud83d\ude2a\u2764\u203c\ud83d\ude4f\ud83d\ude18\ud83d\udca4\ud83d\ude1b\ud83d\udc95\ud83d\ude4f\ud83d\ude02\ud83d\ude24\ud83d\ude2d\ud83d\ude22\u2764\u2764\u5c0f\u6797\u6817\u3082\u30d5\u30a9\u30ed\u30fc\u3057\u3068\u3044\u3066\u3088\u308d\u3057\u304f", "translator_type": "none", "protected": false, "verified": false, "followers_count": 2412, "friends_count": 2083, "listed_count": 1, "favourites_count": 3455, "statuses_count": 42, "created_at": "Wed Oct 12 12:01:28 +0000 2016", "utc_offset": null, "time_zone": null, "geo_enabled": true, "lang": "ja", "contributors_enabled": false, "is_translator": false, "profile_background_color": "F5F8FA", "profile_background_image_url": "", "profile_background_image_url_https": "", "profile_background_tile": false, "profile_link_color": "1DA1F2", "profile_sidebar_border_color": "C0DEED", "profile_sidebar_fill_color": "DDEEF6", "profile_text_color": "333333", "profile_use_background_image": true, "profile_image_url": "http://pbs.twimg.com/profile_images/864092982416252928/socQmcYH_normal.jpg", "profile_image_url_https": "https://pbs.twimg.com/profile_images/864092982416252928/socQmcYH_normal.jpg", "profile_banner_url": "https://pbs.twimg.com/profile_banners/786174948284862464/1502284814", "default_profile": true, "default_profile_image": false, "following": null, "follow_request_sent": null, "notifications": null}, "geo": null, "coordinates": null, "place": {"id": "de41e0d24ed75302", "url": "https://api.twitter.com/1.1/geo/id/de41e0d24ed75302.json", "place_type": "city", "name": "\u6a2a\u6d5c\u5e02 \u702c\u8c37\u533a", "full_name": "\u795e\u5948 \u6a2a\u6d5c\u5e02 \u702c\u8c37\u533a", "country_code": "JP", "country": "\u65e5\u672c", "bounding_box": {"type": "Polygon", "coordinates": [[[139.471283, 35.4319], [139.471283, 35.501907], [139.512256, 35.501907], [139.512256, 35.4319]]]}, "attributes": {}}, "contributors": null, "is_quote_status": false, "quote_count": 0, "reply_count": 0, "retweet_count": 0, "favorite_count": 0, "entities": {"hashtags": [], "urls": [], "user_mentions": [], "symbols": []}, "favorited": false, "retweeted": false, "filter_level": "low", "lang": "ja", "timestamp_ms": "1506208749618"}