{"created_at": "Mon Sep 25 05:10:25 +0000 2017", "id": 912182481364881408, "id_str": "912182481364881408", "text": "I'm at \u4e2d\u90e8\u56fd\u969b\u7a7a\u6e2f \u30bb\u30f3\u30c8\u30ec\u30a2 - @centrairairport in \u5e38\u6ed1\u5e02, \u611b\u77e5\u770c https://t.co/NQ5JGCFv4J", "source": "<a href=\"http://foursquare.com\" rel=\"nofollow\">Foursquare</a>", "truncated": false, "in_reply_to_status_id": null, "in_reply_to_status_id_str": null, "in_reply_to_user_id": null, "in_reply_to_user_id_str": null, "in_reply_to_screen_name": null, "user": {"id": 358769277, "id_str": "358769277", "name": "\u3074\u308d\u307d\u3093", "screen_name": "pilopon777", "location": "\u5c90\u961c \u5c90\u961c\u5e02", "url": "http://profile.ameba.jp/pilopon777/", "description": "\u77e2\u91ce\u7f8e\u512a (MAPLEZ) \uff0f Ritsuka\u2605 (\u30a2\u30f3\u30c9\u30af\u30ec\u30a4\u30b8\u30fc) \uff0f \u77f3\u585a\u6c50\u82b1 (\u30a2\u30a4\u30c9\u30eb\u30ab\u30ec\u30c3\u30b8) \uff0f \u5c0f\u5009\u3042\u3093 (\u714c\u3081\u304d\u2606\u30a2\u30f3\u30d5\u30a9\u30ec\u30f3\u30c8) \uff0f \u9326\u6238\u5f69\u590f (\u30d1\u30d4\u30de\u30b7\u30a7) \uff0f \u6d6a\u6cbb\u5f69\u82b1 (QunQun) \uff0f \u67f4\u7530\u3086\u3044\u304b (\u3048\u304f\u308c\u3042\u30a8\u30af\u30ec\u30c3\u30c8)", "translator_type": "none", "protected": false, "verified": false, "followers_count": 1282, "friends_count": 1926, "listed_count": 16, "favourites_count": 10857, "statuses_count": 20181, "created_at": "Sat Aug 20 13:33:27 +0000 2011", "utc_offset": 32400, "time_zone": "Tokyo", "geo_enabled": true, "lang": "ja", "contributors_enabled": false, "is_translator": false, "profile_background_color": "C0DEED", "profile_background_image_url": "http://pbs.twimg.com/profile_background_images/411175670/358769277-nFgvBH8EPivCunOKNXC5PPdiL5b7ljSpBJt61CC01129260655.jpg", "profile_background_image_url_https": "https://pbs.twimg.com/profile_background_images/411175670/358769277-nFgvBH8EPivCunOKNXC5PPdiL5b7ljSpBJt61CC01129260655.jpg", "profile_background_tile": true, "profile_link_color": "0084B4", "profile_sidebar_border_color": "C0DEED", "profile_sidebar_fill_color": "DDEEF6", "profile_text_color": "333333", "profile_use_background_image": true, "profile_image_url": "http://pbs.twimg.com/profile_images/880217716803592192/Ds11YwdC_normal.jpg", "profile_image_url_https": "https://pbs.twimg.com/profile_images/880217716803592192/Ds11YwdC_normal.jpg", "profile_banner_url": "https://pbs.twimg.com/profile_banners/358769277/1478353653", "default_profile": false, "default_profile_image": false, "following": null, "follow_request_sent": null, "notifications": null}, "geo": {"type": "Point", "coordinates": [34.85936299, 136.81492408]}, "coordinates": {"type": "Point", "coordinates": [136.81492408, 34.85936299]}, "place": {"id": "52e02ff7836ce9d5", "url": "https://api.twitter.com/1.1/geo/id/52e02ff7836ce9d5.json", "place_type": "city", "name": "\u5e38\u6ed1\u5e02", "full_name": "\u611b\u77e5 \u5e38\u6ed1\u5e02", "country_code": "JP", "country": "\u65e5\u672c", "bounding_box": {"type": "Polygon", "coordinates": [[[136.798517, 34.812399], [136.798517, 34.942615], [136.89251, 34.942615], [136.89251, 34.812399]]]}, "attributes": {}}, "contributors": null, "is_quote_status": false, "quote_count": 0, "reply_count": 0, "retweet_count": 0, "favorite_count": 0, "entities": {"hashtags": [], "urls": [{"url": "https://t.co/NQ5JGCFv4J", "expanded_url": "https://www.swarmapp.com/c/3HSrMGcMH4Q", "display_url": "swarmapp.com/c/3HSrMGcMH4Q", "indices": [51, 74]}], "user_mentions": [{"screen_name": "Centrairairport", "name": "\u4e2d\u90e8\u56fd\u969b\u7a7a\u6e2f\u30bb\u30f3\u30c8\u30ec\u30a2", "id": 104960458, "id_str": "104960458", "indices": [22, 38]}], "symbols": []}, "favorited": false, "retweeted": false, "possibly_sensitive": false, "filter_level": "low", "lang": "ja", "timestamp_ms": "1506316225745"}