{"created_at": "Tue Oct 17 19:50:52 +0000 2017", "id": 920376585685004288, "id_str": "920376585685004288", "text": "Damn who at Pinch is willingly taking on other peoples shifts? Send them my number smh https://t.co/UnY0ivs86Y", "display_text_range": [0, 86], "source": "<a href=\"http://twitter.com/download/iphone\" rel=\"nofollow\">Twitter for iPhone</a>", "truncated": false, "in_reply_to_status_id": null, "in_reply_to_status_id_str": null, "in_reply_to_user_id": null, "in_reply_to_user_id_str": null, "in_reply_to_screen_name": null, "user": {"id": 811819328, "id_str": "811819328", "name": "Richard Wheeler", "screen_name": "RichardtWheeler", "location": null, "url": null, "description": null, "translator_type": "none", "protected": false, "verified": false, "followers_count": 546, "friends_count": 40, "listed_count": 8, "favourites_count": 84462, "statuses_count": 33654, "created_at": "Sat Sep 08 22:31:41 +0000 2012", "utc_offset": -10800, "time_zone": "Atlantic Time (Canada)", "geo_enabled": true, "lang": "en", "contributors_enabled": false, "is_translator": false, "profile_background_color": "C0DEED", "profile_background_image_url": "http://pbs.twimg.com/profile_background_images/568451069273837568/okhy8yaO.jpeg", "profile_background_image_url_https": "https://pbs.twimg.com/profile_background_images/568451069273837568/okhy8yaO.jpeg", "profile_background_tile": true, "profile_link_color": "0084B4", "profile_sidebar_border_color": "C0DEED", "profile_sidebar_fill_color": "DDEEF6", "profile_text_color": "333333", "profile_use_background_image": true, "profile_image_url": "http://pbs.twimg.com/profile_images/913196252006899713/b2iXwSG9_normal.jpg", "profile_image_url_https": "https://pbs.twimg.com/profile_images/913196252006899713/b2iXwSG9_normal.jpg", "profile_banner_url": "https://pbs.twimg.com/profile_banners/811819328/1505855032", "default_profile": false, "default_profile_image": false, "following": null, "follow_request_sent": null, "notifications": null}, "geo": null, "coordinates": null, "place": {"id": "6613abf67d2b0d39", "url": "https://api.twitter.com/1.1/geo/id/6613abf67d2b0d39.json", "place_type": "city", "name": "Palm Coast", "full_name": "Palm Coast, FL", "country_code": "US", "country": "United States", "bounding_box": {"type": "Polygon", "coordinates": [[[-81.279617, 29.424649], [-81.279617, 29.627243], [-81.158741, 29.627243], [-81.158741, 29.424649]]]}, "attributes": {}}, "contributors": null, "quoted_status_id": 920372635992842241, "quoted_status_id_str": "920372635992842241", "quoted_status": {"created_at": "Tue Oct 17 19:35:10 +0000 2017", "id": 920372635992842241, "id_str": "920372635992842241", "text": "Me: I work too much this week\nAlso me when coworker asks to cover my shift: It's okay I need the hours", "source": "<a href=\"http://twitter.com/download/iphone\" rel=\"nofollow\">Twitter for iPhone</a>", "truncated": false, "in_reply_to_status_id": null, "in_reply_to_status_id_str": null, "in_reply_to_user_id": null, "in_reply_to_user_id_str": null, "in_reply_to_screen_name": null, "user": {"id": 2230947239, "id_str": "2230947239", "name": "Justin", "screen_name": "TheRealjMaccc", "location": null, "url": null, "description": "Keep me where the light is", "translator_type": "none", "protected": false, "verified": false, "followers_count": 1170, "friends_count": 429, "listed_count": 2, "favourites_count": 23997, "statuses_count": 8137, "created_at": "Wed Dec 18 01:11:08 +0000 2013", "utc_offset": null, "time_zone": null, "geo_enabled": true, "lang": "en", "contributors_enabled": false, "is_translator": false, "profile_background_color": "C0DEED", "profile_background_image_url": "http://abs.twimg.com/images/themes/theme1/bg.png", "profile_background_image_url_https": "https://abs.twimg.com/images/themes/theme1/bg.png", "profile_background_tile": false, "profile_link_color": "1DA1F2", "profile_sidebar_border_color": "C0DEED", "profile_sidebar_fill_color": "DDEEF6", "profile_text_color": "333333", "profile_use_background_image": true, "profile_image_url": "http://pbs.twimg.com/profile_images/906279892832145408/oWIunxo__normal.jpg", "profile_image_url_https": "https://pbs.twimg.com/profile_images/906279892832145408/oWIunxo__normal.jpg", "profile_banner_url": "https://pbs.twimg.com/profile_banners/2230947239/1505452588", "default_profile": true, "default_profile_image": false, "following": null, "follow_request_sent": null, "notifications": null}, "geo": null, "coordinates": null, "place": null, "contributors": null, "is_quote_status": false, "quote_count": 0, "reply_count": 0, "retweet_count": 0, "favorite_count": 4, "entities": {"hashtags": [], "urls": [], "user_mentions": [], "symbols": []}, "favorited": false, "retweeted": false, "filter_level": "low", "lang": "en"}, "is_quote_status": true, "quote_count": 0, "reply_count": 0, "retweet_count": 0, "favorite_count": 0, "entities": {"hashtags": [], "urls": [{"url": "https://t.co/UnY0ivs86Y", "expanded_url": "https://twitter.com/therealjmaccc/status/920372635992842241", "display_url": "twitter.com/therealjmaccc/\u2026", "indices": [87, 110]}], "user_mentions": [], "symbols": []}, "favorited": false, "retweeted": false, "possibly_sensitive": false, "filter_level": "low", "lang": "en", "timestamp_ms": "1508269852454"}