{"text": "Cerramos hoy dos d\u00edas de experiencias nuevas en Madrid con #eltrabajodetussue\u00f1os\nGracias a todos los alumnos de\u2026 https://t.co/25E2Zi5wQI", "extended_tweet": {"full_text": "Cerramos hoy dos d\u00edas de experiencias nuevas en Madrid con #eltrabajodetussue\u00f1os\nGracias a todos los alumnos de @unicomplutense  y @La_UPM  por la gran participaci\u00f3n.\nLos trabajos del futuro estar\u00e1n bien cubiertos por grandes profesionales como vosotros.\n\u00a1GRACIAS A TODOS! https://t.co/wx6txCqxft", "extended_entities": {"media": [{"url": "https://t.co/wx6txCqxft", "expanded_url": "https://twitter.com/AdeccoJovenes/status/930890947973517313/photo/1", "id_str": "930890917023797248", "indices": [273, 296], "id": 930890917023797248, "display_url": "pic.twitter.com/wx6txCqxft", "sizes": {"thumb": {"h": 150, "w": 150, "resize": "crop"}, "large": {"h": 864, "w": 864, "resize": "fit"}, "medium": {"h": 864, "w": 864, "resize": "fit"}, "small": {"h": 680, "w": 680, "resize": "fit"}}, "type": "photo", "media_url_https": "https://pbs.twimg.com/media/DOswW2HXUAAz0Z4.jpg", "media_url": "http://pbs.twimg.com/media/DOswW2HXUAAz0Z4.jpg"}, {"url": "https://t.co/wx6txCqxft", "expanded_url": "https://twitter.com/AdeccoJovenes/status/930890947973517313/photo/1", "id_str": "930890927798996992", "indices": [273, 296], "id": 930890927798996992, "display_url": "pic.twitter.com/wx6txCqxft", "sizes": {"thumb": {"h": 150, "w": 150, "resize": "crop"}, "large": {"h": 864, "w": 864, "resize": "fit"}, "medium": {"h": 864, "w": 864, "resize": "fit"}, "small": {"h": 680, "w": 680, "resize": "fit"}}, "type": "photo", "media_url_https": "https://pbs.twimg.com/media/DOswXeQX0AAR80C.jpg", "media_url": "http://pbs.twimg.com/media/DOswXeQX0AAR80C.jpg"}, {"url": "https://t.co/wx6txCqxft", "expanded_url": "https://twitter.com/AdeccoJovenes/status/930890947973517313/photo/1", "id_str": "930890936099508225", "indices": [273, 296], "id": 930890936099508225, "display_url": "pic.twitter.com/wx6txCqxft", "sizes": {"thumb": {"h": 150, "w": 150, "resize": "crop"}, "small": {"h": 510, "w": 680, "resize": "fit"}, "large": {"h": 750, "w": 1000, "resize": "fit"}, "medium": {"h": 750, "w": 1000, "resize": "fit"}}, "type": "photo", "media_url_https": "https://pbs.twimg.com/media/DOswX9LXkAEuhWY.jpg", "media_url": "http://pbs.twimg.com/media/DOswX9LXkAEuhWY.jpg"}]}, "display_text_range": [0, 272], "entities": {"symbols": [], "user_mentions": [{"screen_name": "unicomplutense", "id_str": "85343435", "indices": [112, 127], "id": 85343435, "name": "Complutense"}, {"screen_name": "La_UPM", "id_str": "395174441", "indices": [131, 138], "id": 395174441, "name": "Polit\u00e9cnica Madrid"}], "hashtags": [{"text": "eltrabajodetussue\u00f1os", "indices": [59, 80]}], "media": [{"url": "https://t.co/wx6txCqxft", "expanded_url": "https://twitter.com/AdeccoJovenes/status/930890947973517313/photo/1", "id_str": "930890917023797248", "indices": [273, 296], "id": 930890917023797248, "display_url": "pic.twitter.com/wx6txCqxft", "sizes": {"thumb": {"h": 150, "w": 150, "resize": "crop"}, "large": {"h": 864, "w": 864, "resize": "fit"}, "medium": {"h": 864, "w": 864, "resize": "fit"}, "small": {"h": 680, "w": 680, "resize": "fit"}}, "type": "photo", "media_url_https": "https://pbs.twimg.com/media/DOswW2HXUAAz0Z4.jpg", "media_url": "http://pbs.twimg.com/media/DOswW2HXUAAz0Z4.jpg"}, {"url": "https://t.co/wx6txCqxft", "expanded_url": "https://twitter.com/AdeccoJovenes/status/930890947973517313/photo/1", "id_str": "930890927798996992", "indices": [273, 296], "id": 930890927798996992, "display_url": "pic.twitter.com/wx6txCqxft", "sizes": {"thumb": {"h": 150, "w": 150, "resize": "crop"}, "large": {"h": 864, "w": 864, "resize": "fit"}, "medium": {"h": 864, "w": 864, "resize": "fit"}, "small": {"h": 680, "w": 680, "resize": "fit"}}, "type": "photo", "media_url_https": "https://pbs.twimg.com/media/DOswXeQX0AAR80C.jpg", "media_url": "http://pbs.twimg.com/media/DOswXeQX0AAR80C.jpg"}, {"url": "https://t.co/wx6txCqxft", "expanded_url": "https://twitter.com/AdeccoJovenes/status/930890947973517313/photo/1", "id_str": "930890936099508225", "indices": [273, 296], "id": 930890936099508225, "display_url": "pic.twitter.com/wx6txCqxft", "sizes": {"thumb": {"h": 150, "w": 150, "resize": "crop"}, "small": {"h": 510, "w": 680, "resize": "fit"}, "large": {"h": 750, "w": 1000, "resize": "fit"}, "medium": {"h": 750, "w": 1000, "resize": "fit"}}, "type": "photo", "media_url_https": "https://pbs.twimg.com/media/DOswX9LXkAEuhWY.jpg", "media_url": "http://pbs.twimg.com/media/DOswX9LXkAEuhWY.jpg"}], "urls": []}}, "geo": null, "id": 930890947973517313, "in_reply_to_status_id_str": null, "contributors": null, "timestamp_ms": "1510776671771", "source": "<a href=\"http://twitter.com/download/android\" rel=\"nofollow\">Twitter for Android</a>", "user": {"screen_name": "AdeccoJovenes", "url": null, "geo_enabled": true, "id": 927470859752804352, "location": null, "verified": false, "time_zone": "Pacific Time (US & Canada)", "default_profile_image": false, "notifications": null, "profile_banner_url": "https://pbs.twimg.com/profile_banners/927470859752804352/1510566311", "protected": false, "default_profile": true, "profile_link_color": "1DA1F2", "listed_count": 0, "favourites_count": 2, "profile_background_image_url": "", "profile_background_color": "F5F8FA", "profile_image_url": "http://pbs.twimg.com/profile_images/927516269187928064/pPlxfLZw_normal.jpg", "is_translator": false, "created_at": "Mon Nov 06 09:40:59 +0000 2017", "name": "Adecco J\u00f3venes", "profile_background_tile": false, "id_str": "927470859752804352", "translator_type": "none", "profile_background_image_url_https": "", "profile_image_url_https": "https://pbs.twimg.com/profile_images/927516269187928064/pPlxfLZw_normal.jpg", "description": "Adecco J\u00f3venes es una comunidad creada para estar m\u00e1s cerca de los j\u00f3venes. Durante el mes de Noviembre llevamos a cabo el proyecto \"El trabajo de tus sue\u00f1os\"", "profile_use_background_image": true, "contributors_enabled": false, "profile_sidebar_border_color": "C0DEED", "lang": "es", "profile_sidebar_fill_color": "DDEEF6", "friends_count": 15, "followers_count": 63, "follow_request_sent": null, "statuses_count": 28, "utc_offset": -28800, "following": null, "profile_text_color": "333333"}, "possibly_sensitive": false, "retweeted": false, "filter_level": "low", "created_at": "Wed Nov 15 20:11:11 +0000 2017", "reply_count": 0, "in_reply_to_user_id_str": null, "favorite_count": 0, "display_text_range": [0, 140], "id_str": "930890947973517313", "place": {"url": "https://api.twitter.com/1.1/geo/id/206c436ce43a43a3.json", "full_name": "Madrid, Espa\u00f1a", "country": "Espa\u00f1a", "id": "206c436ce43a43a3", "country_code": "ES", "attributes": {}, "place_type": "city", "name": "Madrid", "bounding_box": {"coordinates": [[[-3.889005, 40.312071], [-3.889005, 40.643518], [-3.51801, 40.643518], [-3.51801, 40.312071]]], "type": "Polygon"}}, "retweet_count": 0, "coordinates": null, "in_reply_to_screen_name": null, "is_quote_status": false, "quote_count": 0, "lang": "es", "in_reply_to_user_id": null, "truncated": true, "in_reply_to_status_id": null, "favorited": false, "entities": {"symbols": [], "user_mentions": [], "hashtags": [{"text": "eltrabajodetussue\u00f1os", "indices": [59, 80]}], "urls": [{"url": "https://t.co/25E2Zi5wQI", "expanded_url": "https://twitter.com/i/web/status/930890947973517313", "display_url": "twitter.com/i/web/status/9\u2026", "indices": [113, 136]}]}}