{
  "source": "<a href=\"http://twitter.com\" rel=\"nofollow\">Twitter Web Client</a>",
  "in_reply_to_status_id_str": null,
  "favorited": false,
  "in_reply_to_user_id": null,
  "geo": null,
  "in_reply_to_screen_name": null,
  "text": "preparing to visit a friend :D And we're gonna watch Twilight! Yay!",
  "in_reply_to_status_id": null,
  "contributors": null,
  "place": null,
  "truncated": false,
  "retweeted": false,
  "entities": {
    "urls": [],
    "symbols": [],
    "user_mentions": [],
    "hashtags": []
  },
  "lang": "en",
  "retweet_count": 0,
  "coordinates": null,
  "id_str": "1753678426",
  "in_reply_to_user_id_str": null,
  "favorite_count": 0,
  "id": 1753678426,
  "user": {
    "profile_background_image_url": "http://pbs.twimg.com/profile_background_images/48676461/nvnaturalexpression.br.jpg",
    "utc_offset": 3600,
    "default_profile": false,
    "profile_background_image_url_https": "https://pbs.twimg.com/profile_background_images/48676461/nvnaturalexpression.br.jpg",
    "url": "https://t.co/jHNLFqdpZn",
    "favourites_count": 108,
    "protected": false,
    "default_profile_image": false,
    "lang": "en",
    "profile_text_color": "000000",
    "profile_sidebar_fill_color": "432623",
    "profile_use_background_image": true,
    "followers_count": 66,
    "verified": false,
    "location": "Norway",
    "listed_count": 5,
    "screen_name": "MidnightMinx90",
    "name": "Mia",
    "profile_sidebar_border_color": "832020",
    "statuses_count": 24999,
    "profile_banner_url": "https://pbs.twimg.com/profile_banners/39022094/1405712028",
    "entities": {
      "url": {
        "urls": [
          {
            "expanded_url": "https://www.facebook.com/QueenofGlaciaCosplays/",
            "display_url": "facebook.com/QueenofGlaciaC\u2026",
            "url": "https://t.co/jHNLFqdpZn",
            "indices": [
              0,
              23
            ]
          }
        ]
      },
      "description": {
        "urls": []
      }
    },
    "friends_count": 110,
    "has_extended_profile": false,
    "is_translator": false,
    "is_translation_enabled": false,
    "contributors_enabled": false,
    "profile_background_tile": false,
    "geo_enabled": true,
    "id_str": "39022094",
    "profile_link_color": "B80404",
    "follow_request_sent": false,
    "profile_image_url": "http://pbs.twimg.com/profile_images/661296354862452736/JBGg6iAZ_normal.jpg",
    "profile_image_url_https": "https://pbs.twimg.com/profile_images/661296354862452736/JBGg6iAZ_normal.jpg",
    "created_at": "Sun May 10 09:08:42 +0000 2009",
    "id": 39022094,
    "description": "Assassin, N7, Gray Warden, Inquisitor, Dragonborn, Blood, Witch, cosplayer, Wildcard",
    "time_zone": "Copenhagen",
    "profile_background_color": "000000",
    "translator_type": "none",
    "following": false,
    "notifications": false
  },
  "is_quote_status": false,
  "created_at": "Sun May 10 09:52:00 +0000 2009"
}