{
  "in_reply_to_user_id": null,
  "contributors": null,
  "in_reply_to_screen_name": null,
  "retweeted": false,
  "retweet_count": 0,
  "timestamp_ms": "1508694869143",
  "in_reply_to_status_id": null,
  "id_str": "922159234883702784",
  "created_at": "Sun Oct 22 17:54:29 +0000 2017",
  "id": 922159234883702784,
  "coordinates": {
    "type": "Point",
    "coordinates": [
      -58.5833,
      -34.5333
    ]
  },
  "favorite_count": 0,
  "entities": {
    "user_mentions": [],
    "symbols": [],
    "hashtags": [],
    "urls": [
      {
        "expanded_url": "https://www.instagram.com/p/BajzUhGHWnVZ6h-Bwjxc_NNa4ezmCxSMuLjyCg0/",
        "indices": [
          65,
          88
        ],
        "url": "https://t.co/fG6VozjQ5d",
        "display_url": "instagram.com/p/BajzUhGHWnVZ\u2026"
      }
    ]
  },
  "reply_count": 0,
  "source": "<a href=\"http://instagram.com\" rel=\"nofollow\">Instagram</a>",
  "place": {
    "attributes": {},
    "url": "https://api.twitter.com/1.1/geo/id/004b853c78703c20.json",
    "place_type": "city",
    "id": "004b853c78703c20",
    "country_code": "AR",
    "name": "Ciudad del Libertador General San Mart\u00edn",
    "country": "Argentina",
    "bounding_box": {
      "type": "Polygon",
      "coordinates": [
        [
          [
            -58.618436,
            -34.597406
          ],
          [
            -58.618436,
            -34.491912
          ],
          [
            -58.509913,
            -34.491912
          ],
          [
            -58.509913,
            -34.597406
          ]
        ]
      ]
    },
    "full_name": "Ciudad del Libertador General San Mart\u00edn, Argentina"
  },
  "truncated": false,
  "in_reply_to_status_id_str": null,
  "filter_level": "low",
  "text": "Toda la vida enamorada de vos, de tus besos y abrazos, feliz de\u2026 https://t.co/fG6VozjQ5d",
  "geo": {
    "type": "Point",
    "coordinates": [
      -34.5333,
      -58.5833
    ]
  },
  "in_reply_to_user_id_str": null,
  "is_quote_status": false,
  "possibly_sensitive": false,
  "favorited": false,
  "user": {
    "verified": false,
    "profile_background_image_url": "http://pbs.twimg.com/profile_background_images/696403054200037377/T35qwv_v.jpg",
    "statuses_count": 39492,
    "screen_name": "MilaagrosCai",
    "default_profile_image": false,
    "time_zone": "Buenos Aires",
    "name": "Independien7e\u03a8",
    "id_str": "440455314",
    "profile_sidebar_border_color": "FFFFFF",
    "profile_banner_url": "https://pbs.twimg.com/profile_banners/440455314/1489711161",
    "created_at": "Mon Dec 19 01:08:03 +0000 2011",
    "friends_count": 2331,
    "url": "https://www.instagram.com/milaagroscai/",
    "profile_background_tile": true,
    "protected": false,
    "translator_type": "none",
    "profile_text_color": "333333",
    "profile_image_url_https": "https://pbs.twimg.com/profile_images/874808956828479489/GB3Og3U0_normal.jpg",
    "listed_count": 3,
    "notifications": null,
    "contributors_enabled": false,
    "is_translator": false,
    "location": "Gerli",
    "profile_use_background_image": true,
    "followers_count": 2428,
    "profile_sidebar_fill_color": "DDEEF6",
    "geo_enabled": true,
    "profile_link_color": "981CEB",
    "favourites_count": 2172,
    "following": null,
    "default_profile": false,
    "profile_background_image_url_https": "https://pbs.twimg.com/profile_background_images/696403054200037377/T35qwv_v.jpg",
    "profile_background_color": "1A1B1F",
    "id": 440455314,
    "profile_image_url": "http://pbs.twimg.com/profile_images/874808956828479489/GB3Og3U0_normal.jpg",
    "lang": "es",
    "description": "|Vivirlo con vos para mi es la gloria [ @ExequielMTagle ]| Desde el cielo me guian tus ojos| Gerli| Desde 1999 siguiendo a independiente|\ud83d\udc25 @Sauraspromo17 |",
    "follow_request_sent": null,
    "utc_offset": -10800
  },
  "quote_count": 0,
  "lang": "es"
}